zappa_sentry/__init__.py
zappa_sentry-0.4.0.dist-info/DESCRIPTION.rst
zappa_sentry-0.4.0.dist-info/METADATA
zappa_sentry-0.4.0.dist-info/RECORD
zappa_sentry-0.4.0.dist-info/WHEEL
zappa_sentry-0.4.0.dist-info/metadata.json
zappa_sentry-0.4.0.dist-info/top_level.txt
