Metadata-Version: 2.0
Name: zappa-sentry
Version: 0.4.0
Summary: Easy integration with sentry for zappa apps
Home-page: https://github.com/jneves/zappa-sentry
Author: João Miguel Neves
Author-email: joao@silvaneves.org
License: UNKNOWN
Download-URL: https://github.com/jneves/zappa-sentry/archive/0.2.3.tar.gz
Keywords: logging zappa sentry
Platform: UNKNOWN
Classifier: Development Status :: 3 - Alpha
Classifier: Intended Audience :: Developers
Classifier: License :: OSI Approved :: MIT License
Classifier: Programming Language :: Python :: 2.7
Classifier: Programming Language :: Python :: 3.6
Requires-Dist: sentry-sdk
